{
    "RevertDepthCreateAddressCollision": {
        "expect": [
            {
                "indexes": {
                    "data": 1,
                    "gas": 1,
                    "value": 0
                },
                "network": [
                    ">=Cancun"
                ],
                "result": {
                    "0xB000000000000000000000000000000000000000": {
                        "nonce": "0x00",
                        "balance": "0x00",
                        "code": "0x6008600255600060006000f050600c60035500000000000000000000000000000000000000000000000000000000000000000000",
                        "storage": {
                            "0x03": "0x00",
                            "0x02": "0x00"
                        }
                    },
                    "0xa94f5374Fce5edBC8E2a8697C15331677e6EbF0B": {
                        "nonce": "0x01",
                        "balance": "0xe8d48ca600",
                        "code": "0x000000000000000000000000000000000000000000000000000000000000000000",
                        "storage": {}
                    },
                    "0x3e180B1862f9d158aBb5E519a6D8605540C23682": {
                        "nonce": "0x36",
                        "balance": "0x05",
                        "code": "0x60016000556000600060006000600073b000000000000000000000000000000000000000600035f1600155600c60045500000000000000000000000000000000000000000000000000000000000000000000",
                        "storage": {
                            "0x00": "0x00",
                            "0x01": "0x00"
                        }
                    },
                    "0x2ADC25665018Aa1FE0E6BC666DaC8Fc2697fF9bA": {
                        "shouldnotexist": "1"
                    }
                }
            },
            {
                "indexes": {
                    "data": 1,
                    "gas": 1,
                    "value": 1
                },
                "network": [
                    ">=Cancun"
                ],
                "result": {
                    "0x3e180B1862f9d158aBb5E519a6D8605540C23682": {
                        "nonce": "0x36",
                        "balance": "0x05",
                        "code": "0x60016000556000600060006000600073b000000000000000000000000000000000000000600035f1600155600c60045500000000000000000000000000000000000000000000000000000000000000000000",
                        "storage": {
                            "0x00": "0x00",
                            "0x01": "0x00"
                        }
                    },
                    "0xa94f5374Fce5edBC8E2a8697C15331677e6EbF0B": {
                        "nonce": "0x01",
                        "balance": "0xe8d48ca600",
                        "code": "0x000000000000000000000000000000000000000000000000000000000000000000",
                        "storage": {}
                    },
                    "0x2ADC25665018Aa1FE0E6BC666DaC8Fc2697fF9bA": {
                        "shouldnotexist": "1"
                    },
                    "0xB000000000000000000000000000000000000000": {
                        "nonce": "0x00",
                        "balance": "0x00",
                        "code": "0x6008600255600060006000f050600c60035500000000000000000000000000000000000000000000000000000000000000000000",
                        "storage": {
                            "0x02": "0x00",
                            "0x03": "0x00"
                        }
                    }
                }
            },
            {
                "indexes": {
                    "data": 0,
                    "gas": 1,
                    "value": 0
                },
                "network": [
                    ">=Cancun"
                ],
                "result": {
                    "0x3e180B1862f9d158aBb5E519a6D8605540C23682": {
                        "nonce": "0x36",
                        "balance": "0x06",
                        "code": "0x60016000556000600060006000600073b000000000000000000000000000000000000000600035f1600155600c60045500000000000000000000000000000000000000000000000000000000000000000000",
                        "storage": {
                            "0x00": "0x01",
                            "0x04": "0x0c",
                            "0x01": "0x00"
                        }
                    },
                    "0xB000000000000000000000000000000000000000": {
                        "nonce": "0x00",
                        "balance": "0x00",
                        "code": "0x6008600255600060006000f050600c60035500000000000000000000000000000000000000000000000000000000000000000000",
                        "storage": {
                            "0x03": "0x00",
                            "0x02": "0x00"
                        }
                    },
                    "0xa94f5374Fce5edBC8E2a8697C15331677e6EbF0B": {
                        "nonce": "0x01",
                        "balance": "0xe8d4913269",
                        "code": "0x000000000000000000000000000000000000000000000000000000000000000000",
                        "storage": {}
                    },
                    "0x2ADC25665018Aa1FE0E6BC666DaC8Fc2697fF9bA": {
                        "shouldnotexist": "1"
                    }
                }
            },
            {
                "indexes": {
                    "data": 0,
                    "gas": 1,
                    "value": 1
                },
                "network": [
                    ">=Cancun"
                ],
                "result": {
                    "0xB000000000000000000000000000000000000000": {
                        "nonce": "0x00",
                        "balance": "0x00",
                        "code": "0x6008600255600060006000f050600c60035500000000000000000000000000000000000000000000000000000000000000000000",
                        "storage": {
                            "0x02": "0x00",
                            "0x03": "0x00"
                        }
                    },
                    "0x2ADC25665018Aa1FE0E6BC666DaC8Fc2697fF9bA": {
                        "shouldnotexist": "1"
                    },
                    "0x3e180B1862f9d158aBb5E519a6D8605540C23682": {
                        "nonce": "0x36",
                        "balance": "0x05",
                        "code": "0x60016000556000600060006000600073b000000000000000000000000000000000000000600035f1600155600c60045500000000000000000000000000000000000000000000000000000000000000000000",
                        "storage": {
                            "0x00": "0x01",
                            "0x01": "0x00",
                            "0x04": "0x0c"
                        }
                    },
                    "0xa94f5374Fce5edBC8E2a8697C15331677e6EbF0B": {
                        "nonce": "0x01",
                        "balance": "0xe8d491326a",
                        "code": "0x000000000000000000000000000000000000000000000000000000000000000000",
                        "storage": {}
                    }
                }
            },
            {
                "indexes": {
                    "data": 1,
                    "gas": 0,
                    "value": 0
                },
                "network": [
                    ">=Cancun"
                ],
                "result": {
                    "0x2ADC25665018Aa1FE0E6BC666DaC8Fc2697fF9bA": {
                        "shouldnotexist": "1"
                    },
                    "0xB000000000000000000000000000000000000000": {
                        "nonce": "0x00",
                        "balance": "0x00",
                        "code": "0x6008600255600060006000f050600c60035500000000000000000000000000000000000000000000000000000000000000000000",
                        "storage": {
                            "0x02": "0x00",
                            "0x03": "0x00"
                        }
                    },
                    "0xa94f5374Fce5edBC8E2a8697C15331677e6EbF0B": {
                        "nonce": "0x01",
                        "balance": "0xe8d4944720",
                        "code": "0x000000000000000000000000000000000000000000000000000000000000000000",
                        "storage": {}
                    },
                    "0x3e180B1862f9d158aBb5E519a6D8605540C23682": {
                        "nonce": "0x36",
                        "balance": "0x05",
                        "code": "0x60016000556000600060006000600073b000000000000000000000000000000000000000600035f1600155600c60045500000000000000000000000000000000000000000000000000000000000000000000",
                        "storage": {
                            "0x01": "0x00",
                            "0x00": "0x00"
                        }
                    }
                }
            },
            {
                "indexes": {
                    "data": 1,
                    "gas": 0,
                    "value": 1
                },
                "network": [
                    ">=Cancun"
                ],
                "result": {
                    "0xa94f5374Fce5edBC8E2a8697C15331677e6EbF0B": {
                        "nonce": "0x01",
                        "balance": "0xe8d4944720",
                        "code": "0x000000000000000000000000000000000000000000000000000000000000000000",
                        "storage": {}
                    },
                    "0xB000000000000000000000000000000000000000": {
                        "nonce": "0x00",
                        "balance": "0x00",
                        "code": "0x6008600255600060006000f050600c60035500000000000000000000000000000000000000000000000000000000000000000000",
                        "storage": {
                            "0x03": "0x00",
                            "0x02": "0x00"
                        }
                    },
                    "0x3e180B1862f9d158aBb5E519a6D8605540C23682": {
                        "nonce": "0x36",
                        "balance": "0x05",
                        "code": "0x60016000556000600060006000600073b000000000000000000000000000000000000000600035f1600155600c60045500000000000000000000000000000000000000000000000000000000000000000000",
                        "storage": {
                            "0x00": "0x00",
                            "0x01": "0x00"
                        }
                    },
                    "0x2ADC25665018Aa1FE0E6BC666DaC8Fc2697fF9bA": {
                        "shouldnotexist": "1"
                    }
                }
            },
            {
                "indexes": {
                    "data": 0,
                    "gas": 0,
                    "value": 0
                },
                "network": [
                    ">=Cancun"
                ],
                "result": {
                    "0xa94f5374Fce5edBC8E2a8697C15331677e6EbF0B": {
                        "nonce": "0x01",
                        "balance": "0xe8d4944720",
                        "code": "0x000000000000000000000000000000000000000000000000000000000000000000",
                        "storage": {}
                    },
                    "0x2ADC25665018Aa1FE0E6BC666DaC8Fc2697fF9bA": {
                        "shouldnotexist": "1"
                    },
                    "0xB000000000000000000000000000000000000000": {
                        "nonce": "0x00",
                        "balance": "0x00",
                        "code": "0x6008600255600060006000f050600c60035500000000000000000000000000000000000000000000000000000000000000000000",
                        "storage": {
                            "0x02": "0x00",
                            "0x03": "0x00"
                        }
                    },
                    "0x3e180B1862f9d158aBb5E519a6D8605540C23682": {
                        "nonce": "0x36",
                        "balance": "0x05",
                        "code": "0x60016000556000600060006000600073b000000000000000000000000000000000000000600035f1600155600c60045500000000000000000000000000000000000000000000000000000000000000000000",
                        "storage": {
                            "0x04": "0x00",
                            "0x00": "0x00",
                            "0x01": "0x00"
                        }
                    }
                }
            },
            {
                "indexes": {
                    "data": 0,
                    "gas": 0,
                    "value": 1
                },
                "network": [
                    ">=Cancun"
                ],
                "result": {
                    "0x2ADC25665018Aa1FE0E6BC666DaC8Fc2697fF9bA": {
                        "shouldnotexist": "1"
                    },
                    "0xB000000000000000000000000000000000000000": {
                        "nonce": "0x00",
                        "balance": "0x00",
                        "code": "0x6008600255600060006000f050600c60035500000000000000000000000000000000000000000000000000000000000000000000",
                        "storage": {
                            "0x03": "0x00",
                            "0x02": "0x00"
                        }
                    },
                    "0x3e180B1862f9d158aBb5E519a6D8605540C23682": {
                        "nonce": "0x36",
                        "balance": "0x05",
                        "code": "0x60016000556000600060006000600073b000000000000000000000000000000000000000600035f1600155600c60045500000000000000000000000000000000000000000000000000000000000000000000",
                        "storage": {
                            "0x04": "0x00",
                            "0x01": "0x00",
                            "0x00": "0x00"
                        }
                    },
                    "0xa94f5374Fce5edBC8E2a8697C15331677e6EbF0B": {
                        "nonce": "0x01",
                        "balance": "0xe8d4944720",
                        "code": "0x000000000000000000000000000000000000000000000000000000000000000000",
                        "storage": {}
                    }
                }
            },
            {
                "indexes": {
                    "data": 1,
                    "gas": 1,
                    "value": 0
                },
                "network": [
                    ">=Cancun"
                ],
                "result": {
                    "0x05A28Fc366483258507bCF739658573cB47e4fAD": {
                        "nonce": "0x01",
                        "balance": "0x00",
                        "code": "0x000000000000000000000000000000000000000000000000000000000000000000",
                        "storage": {}
                    },
                    "0x3e180B1862f9d158aBb5E519a6D8605540C23682": {
                        "nonce": "0x36",
                        "balance": "0x06",
                        "code": "0x60016000556000600060006000600073b000000000000000000000000000000000000000600035f1600155600c60045500000000000000000000000000000000000000000000000000000000000000000000",
                        "storage": {
                            "0x00": "0x01",
                            "0x04": "0x0c",
                            "0x01": "0x01"
                        }
                    },
                    "0x2ADC25665018Aa1FE0E6BC666DaC8Fc2697fF9bA": {
                        "shouldnotexist": "1"
                    },
                    "0xB000000000000000000000000000000000000000": {
                        "nonce": "0x01",
                        "balance": "0x00",
                        "code": "0x60086002556000600060006000f550600c60035500000000000000000000000000000000000000000000000000000000000000000000",
                        "storage": {
                            "0x02": "0x08",
                            "0x03": "0x0c"
                        }
                    },
                    "0xa94f5374Fce5edBC8E2a8697C15331677e6EbF0B": {
                        "nonce": "0x01",
                        "balance": "0xe8d48baec5",
                        "code": "0x000000000000000000000000000000000000000000000000000000000000000000",
                        "storage": {}
                    }
                }
            },
            {
                "indexes": {
                    "data": 1,
                    "gas": 1,
                    "value": 1
                },
                "network": [
                    ">=Cancun"
                ],
                "result": {
                    "0xa94f5374Fce5edBC8E2a8697C15331677e6EbF0B": {
                        "nonce": "0x01",
                        "balance": "0xe8d48baec6",
                        "code": "0x000000000000000000000000000000000000000000000000000000000000000000",
                        "storage": {}
                    },
                    "0x05A28Fc366483258507bCF739658573cB47e4fAD": {
                        "nonce": "0x01",
                        "balance": "0x00",
                        "code": "0x000000000000000000000000000000000000000000000000000000000000000000",
                        "storage": {}
                    },
                    "0x2ADC25665018Aa1FE0E6BC666DaC8Fc2697fF9bA": {
                        "shouldnotexist": "1"
                    },
                    "0xB000000000000000000000000000000000000000": {
                        "nonce": "0x01",
                        "balance": "0x00",
                        "code": "0x60086002556000600060006000f550600c60035500000000000000000000000000000000000000000000000000000000000000000000",
                        "storage": {
                            "0x03": "0x0c",
                            "0x02": "0x08"
                        }
                    },
                    "0x3e180B1862f9d158aBb5E519a6D8605540C23682": {
                        "nonce": "0x36",
                        "balance": "0x05",
                        "code": "0x60016000556000600060006000600073b000000000000000000000000000000000000000600035f1600155600c60045500000000000000000000000000000000000000000000000000000000000000000000",
                        "storage": {
                            "0x04": "0x0c",
                            "0x01": "0x01",
                            "0x00": "0x01"
                        }
                    }
                }
            },
            {
                "indexes": {
                    "data": 0,
                    "gas": 1,
                    "value": 0
                },
                "network": [
                    ">=Cancun"
                ],
                "result": {
                    "0xa94f5374Fce5edBC8E2a8697C15331677e6EbF0B": {
                        "nonce": "0x01",
                        "balance": "0xe8d4913269",
                        "code": "0x000000000000000000000000000000000000000000000000000000000000000000",
                        "storage": {}
                    },
                    "0x3e180B1862f9d158aBb5E519a6D8605540C23682": {
                        "nonce": "0x36",
                        "balance": "0x06",
                        "code": "0x60016000556000600060006000600073b000000000000000000000000000000000000000600035f1600155600c60045500000000000000000000000000000000000000000000000000000000000000000000",
                        "storage": {
                            "0x00": "0x01",
                            "0x01": "0x00",
                            "0x04": "0x0c"
                        }
                    },
                    "0x05A28Fc366483258507bCF739658573cB47e4fAD": {
                        "shouldnotexist": "1"
                    },
                    "0x2ADC25665018Aa1FE0E6BC666DaC8Fc2697fF9bA": {
                        "shouldnotexist": "1"
                    },
                    "0xB000000000000000000000000000000000000000": {
                        "nonce": "0x00",
                        "balance": "0x00",
                        "code": "0x60086002556000600060006000f550600c60035500000000000000000000000000000000000000000000000000000000000000000000",
                        "storage": {
                            "0x03": "0x00",
                            "0x02": "0x00"
                        }
                    }
                }
            },
            {
                "indexes": {
                    "data": 0,
                    "gas": 1,
                    "value": 1
                },
                "network": [
                    ">=Cancun"
                ],
                "result": {
                    "0xB000000000000000000000000000000000000000": {
                        "nonce": "0x00",
                        "balance": "0x00",
                        "code": "0x60086002556000600060006000f550600c60035500000000000000000000000000000000000000000000000000000000000000000000",
                        "storage": {
                            "0x03": "0x00",
                            "0x02": "0x00"
                        }
                    },
                    "0x2ADC25665018Aa1FE0E6BC666DaC8Fc2697fF9bA": {
                        "shouldnotexist": "1"
                    },
                    "0x3e180B1862f9d158aBb5E519a6D8605540C23682": {
                        "nonce": "0x36",
                        "balance": "0x05",
                        "code": "0x60016000556000600060006000600073b000000000000000000000000000000000000000600035f1600155600c60045500000000000000000000000000000000000000000000000000000000000000000000",
                        "storage": {
                            "0x04": "0x0c",
                            "0x00": "0x01",
                            "0x01": "0x00"
                        }
                    },
                    "0x05A28Fc366483258507bCF739658573cB47e4fAD": {
                        "shouldnotexist": "1"
                    },
                    "0xa94f5374Fce5edBC8E2a8697C15331677e6EbF0B": {
                        "nonce": "0x01",
                        "balance": "0xe8d491326a",
                        "code": "0x000000000000000000000000000000000000000000000000000000000000000000",
                        "storage": {}
                    }
                }
            },
            {
                "indexes": {
                    "data": 1,
                    "gas": 0,
                    "value": 0
                },
                "network": [
                    ">=Cancun"
                ],
                "result": {
                    "0x05A28Fc366483258507bCF739658573cB47e4fAD": {
                        "shouldnotexist": "1"
                    },
                    "0xB000000000000000000000000000000000000000": {
                        "nonce": "0x00",
                        "balance": "0x00",
                        "code": "0x60086002556000600060006000f550600c60035500000000000000000000000000000000000000000000000000000000000000000000",
                        "storage": {
                            "0x03": "0x00",
                            "0x02": "0x00"
                        }
                    },
                    "0xa94f5374Fce5edBC8E2a8697C15331677e6EbF0B": {
                        "nonce": "0x01",
                        "balance": "0xe8d4944720",
                        "code": "0x000000000000000000000000000000000000000000000000000000000000000000",
                        "storage": {}
                    },
                    "0x2ADC25665018Aa1FE0E6BC666DaC8Fc2697fF9bA": {
                        "shouldnotexist": "1"
                    },
                    "0x3e180B1862f9d158aBb5E519a6D8605540C23682": {
                        "nonce": "0x36",
                        "balance": "0x05",
                        "code": "0x60016000556000600060006000600073b000000000000000000000000000000000000000600035f1600155600c60045500000000000000000000000000000000000000000000000000000000000000000000",
                        "storage": {
                            "0x00": "0x00",
                            "0x01": "0x00"
                        }
                    }
                }
            },
            {
                "indexes": {
                    "data": 1,
                    "gas": 0,
                    "value": 1
                },
                "network": [
                    ">=Cancun"
                ],
                "result": {
                    "0xa94f5374Fce5edBC8E2a8697C15331677e6EbF0B": {
                        "nonce": "0x01",
                        "balance": "0xe8d4944720",
                        "code": "0x000000000000000000000000000000000000000000000000000000000000000000",
                        "storage": {}
                    },
                    "0xB000000000000000000000000000000000000000": {
                        "nonce": "0x00",
                        "balance": "0x00",
                        "code": "0x60086002556000600060006000f550600c60035500000000000000000000000000000000000000000000000000000000000000000000",
                        "storage": {
                            "0x03": "0x00",
                            "0x02": "0x00"
                        }
                    },
                    "0x05A28Fc366483258507bCF739658573cB47e4fAD": {
                        "shouldnotexist": "1"
                    },
                    "0x2ADC25665018Aa1FE0E6BC666DaC8Fc2697fF9bA": {
                        "shouldnotexist": "1"
                    },
                    "0x3e180B1862f9d158aBb5E519a6D8605540C23682": {
                        "nonce": "0x36",
                        "balance": "0x05",
                        "code": "0x60016000556000600060006000600073b000000000000000000000000000000000000000600035f1600155600c60045500000000000000000000000000000000000000000000000000000000000000000000",
                        "storage": {
                            "0x01": "0x00",
                            "0x00": "0x00"
                        }
                    }
                }
            },
            {
                "indexes": {
                    "data": 0,
                    "gas": 0,
                    "value": 0
                },
                "network": [
                    ">=Cancun"
                ],
                "result": {
                    "0xa94f5374Fce5edBC8E2a8697C15331677e6EbF0B": {
                        "nonce": "0x01",
                        "balance": "0xe8d4944720",
                        "code": "0x000000000000000000000000000000000000000000000000000000000000000000",
                        "storage": {}
                    },
                    "0x05A28Fc366483258507bCF739658573cB47e4fAD": {
                        "shouldnotexist": "1"
                    },
                    "0x3e180B1862f9d158aBb5E519a6D8605540C23682": {
                        "nonce": "0x36",
                        "balance": "0x05",
                        "code": "0x60016000556000600060006000600073b000000000000000000000000000000000000000600035f1600155600c60045500000000000000000000000000000000000000000000000000000000000000000000",
                        "storage": {
                            "0x01": "0x00",
                            "0x00": "0x00",
                            "0x04": "0x00"
                        }
                    },
                    "0x2ADC25665018Aa1FE0E6BC666DaC8Fc2697fF9bA": {
                        "shouldnotexist": "1"
                    },
                    "0xB000000000000000000000000000000000000000": {
                        "nonce": "0x00",
                        "balance": "0x00",
                        "code": "0x60086002556000600060006000f550600c60035500000000000000000000000000000000000000000000000000000000000000000000",
                        "storage": {
                            "0x03": "0x00",
                            "0x02": "0x00"
                        }
                    }
                }
            },
            {
                "indexes": {
                    "data": 0,
                    "gas": 0,
                    "value": 1
                },
                "network": [
                    ">=Cancun"
                ],
                "result": {
                    "0xB000000000000000000000000000000000000000": {
                        "nonce": "0x00",
                        "balance": "0x00",
                        "code": "0x60086002556000600060006000f550600c60035500000000000000000000000000000000000000000000000000000000000000000000",
                        "storage": {
                            "0x02": "0x00",
                            "0x03": "0x00"
                        }
                    },
                    "0xa94f5374Fce5edBC8E2a8697C15331677e6EbF0B": {
                        "nonce": "0x01",
                        "balance": "0xe8d4944720",
                        "code": "0x000000000000000000000000000000000000000000000000000000000000000000",
                        "storage": {}
                    },
                    "0x3e180B1862f9d158aBb5E519a6D8605540C23682": {
                        "nonce": "0x36",
                        "balance": "0x05",
                        "code": "0x60016000556000600060006000600073b000000000000000000000000000000000000000600035f1600155600c60045500000000000000000000000000000000000000000000000000000000000000000000",
                        "storage": {
                            "0x01": "0x00",
                            "0x00": "0x00",
                            "0x04": "0x00"
                        }
                    },
                    "0x05A28Fc366483258507bCF739658573cB47e4fAD": {
                        "shouldnotexist": "1"
                    },
                    "0x2ADC25665018Aa1FE0E6BC666DaC8Fc2697fF9bA": {
                        "shouldnotexist": "1"
                    }
                }
            }
        ]
    }
}