{
    "create_opcode_initcode": {
        "expect": [
            {
                "indexes": {
                    "data": 0,
                    "gas": 0,
                    "value": 0
                },
                "network": [
                    ">=Shanghai"
                ],
                "expectException": null,
                "result": {
                    "0x0000000000000000000000000000000000000200": {
                        "nonce": "0x01",
                        "balance": "0x00",
                        "code": "0x3660006000376001600060003660006000610100624c4b40f155000000000000000000000000000000000000000000000000000000000000000000",
                        "storage": {
                            "0x00": "0x01"
                        }
                    },
                    "0x0000000000000000000000000000000000000100": {
                        "nonce": "0x01",
                        "balance": "0x00",
                        "code": "0x3660006000375a63deadbeef3660006000f55a906000559003600155000000000000000000000000000000000000000000000000000000000000000000",
                        "storage": {}
                    }
                }
            }
        ]
    }
}